terminalcast/__init__.py
terminalcast/filedata.py
terminalcast/helper.py
terminalcast/tc.py
terminalcast-1.3.2.dist-info/licenses/LICENSE
terminalcast-1.3.2.dist-info/METADATA
terminalcast-1.3.2.dist-info/WHEEL
terminalcast-1.3.2.dist-info/entry_points.txt
terminalcast-1.3.2.dist-info/top_level.txt
terminalcast-1.3.2.dist-info/RECORD
