Metadata-Version: 2.4
Name: terminalcast
Version: 1.3.2
Summary: Cast local videos to your chromecast
Author-email: Johannes Paul <vanadinit@quantentunnel.de>
License: MIT
Project-URL: Homepage, https://github.com/vanadinit/terminalcast
Keywords: Chromecast,video,local,movie
Classifier: Programming Language :: Python :: 3
Classifier: License :: OSI Approved :: MIT License
Requires-Python: >=3.10
License-File: LICENSE
Requires-Dist: bottle
Requires-Dist: ffmpeg-python
Requires-Dist: waitress
Requires-Dist: pychromecast>=13.0.0
Requires-Dist: zeroconf>=0.31.0
Requires-Dist: tqdm
Provides-Extra: dev
Requires-Dist: ruff; extra == "dev"
Requires-Dist: mypy; extra == "dev"
Requires-Dist: pytest; extra == "dev"
Requires-Dist: pre-commit; extra == "dev"
Dynamic: license-file
